{
  "generated_at": "2026-02-28T01:13:36.008305",
  "game": {
    "date": "2025-10-04",
    "home_team": "シーホース三河",
    "away_team": "群馬クレインサンダーズ"
  },
  "teams": {
    "シーホース三河": {
      "players": [
        {
          "team_jba_id": "",
          "jersey_number": "1",
          "player_name": "トーマス ケネディ",
          "stats": {
            "PTS": 0.0,
            "REB": 1.0,
            "AST": 0.0,
            "3PM": 0.0,
            "STL": 0.0,
            "BLK": 0.0,
            "MIN": 13.8167,
            "MIN_display": "13:49"
          },
          "season_high": {
            "PTS": {
              "value": "0.0",
              "date": "2025-10-04",
              "opponent": "群馬クレインサンダーズ",
              "display": "0.0"
            },
            "REB": {
              "value": "1.0",
              "date": "2025-10-04",
              "opponent": "群馬クレインサンダーズ",
              "display": "1.0"
            },
            "AST": {
              "value": "0.0",
              "date": "2025-10-04",
              "opponent": "群馬クレインサンダーズ",
              "display": "0.0"
            },
            "3PM": {
              "value": "0.0",
              "date": "2025-10-04",
              "opponent": "群馬クレインサンダーズ",
              "display": "0.0"
            },
            "STL": {
              "value": "0.0",
              "date": "2025-10-04",
              "opponent": "群馬クレインサンダーズ",
              "display": "0.0"
            },
            "BLK": {
              "value": "0.0",
              "date": "2025-10-04",
              "opponent": "群馬クレインサンダーズ",
              "display": "0.0"
            },
            "MIN": {
              "value": "13.8167",
              "date": "2025-10-04",
              "opponent": "群馬クレインサンダーズ",
              "display": "13:49"
            }
          }
        },
        {
          "team_jba_id": "",
          "jersey_number": "7",
          "player_name": "誠史 長野",
          "stats": {
            "PTS": 5.0,
            "REB": 2.0,
            "AST": 3.0,
            "3PM": 1.0,
            "STL": 2.0,
            "BLK": 0.0,
            "MIN": 15.95,
            "MIN_display": "15:57"
          },
          "season_high": {
            "PTS": {
              "value": "5.0",
              "date": "2025-10-04",
              "opponent": "群馬クレインサンダーズ",
              "display": "5.0"
            },
            "REB": {
              "value": "2.0",
              "date": "2025-10-04",
              "opponent": "群馬クレインサンダーズ",
              "display": "2.0"
            },
            "AST": {
              "value": "3.0",
              "date": "2025-10-04",
              "opponent": "群馬クレインサンダーズ",
              "display": "3.0"
            },
            "3PM": {
              "value": "1.0",
              "date": "2025-10-04",
              "opponent": "群馬クレインサンダーズ",
              "display": "1.0"
            },
            "STL": {
              "value": "2.0",
              "date": "2025-10-04",
              "opponent": "群馬クレインサンダーズ",
              "display": "2.0"
            },
            "BLK": {
              "value": "0.0",
              "date": "2025-10-04",
              "opponent": "群馬クレインサンダーズ",
              "display": "0.0"
            },
            "MIN": {
              "value": "15.95",
              "date": "2025-10-04",
              "opponent": "群馬クレインサンダーズ",
              "display": "15:57"
            }
          }
        },
        {
          "team_jba_id": "",
          "jersey_number": "10",
          "player_name": "ジェイク レイマン",
          "stats": {
            "PTS": 3.0,
            "REB": 7.0,
            "AST": 3.0,
            "3PM": 0.0,
            "STL": 1.0,
            "BLK": 0.0,
            "MIN": 25.9,
            "MIN_display": "25:54"
          },
          "season_high": {
            "PTS": {
              "value": "3.0",
              "date": "2025-10-04",
              "opponent": "群馬クレインサンダーズ",
              "display": "3.0"
            },
            "REB": {
              "value": "7.0",
              "date": "2025-10-04",
              "opponent": "群馬クレインサンダーズ",
              "display": "7.0"
            },
            "AST": {
              "value": "3.0",
              "date": "2025-10-04",
              "opponent": "群馬クレインサンダーズ",
              "display": "3.0"
            },
            "3PM": {
              "value": "0.0",
              "date": "2025-10-04",
              "opponent": "群馬クレインサンダーズ",
              "display": "0.0"
            },
            "STL": {
              "value": "1.0",
              "date": "2025-10-04",
              "opponent": "群馬クレインサンダーズ",
              "display": "1.0"
            },
            "BLK": {
              "value": "0.0",
              "date": "2025-10-04",
              "opponent": "群馬クレインサンダーズ",
              "display": "0.0"
            },
            "MIN": {
              "value": "25.9",
              "date": "2025-10-04",
              "opponent": "群馬クレインサンダーズ",
              "display": "25:54"
            }
          }
        },
        {
          "team_jba_id": "",
          "jersey_number": "11",
          "player_name": "義章 久保田",
          "stats": {
            "PTS": 8.0,
            "REB": 4.0,
            "AST": 1.0,
            "3PM": 2.0,
            "STL": 0.0,
            "BLK": 0.0,
            "MIN": 23.3167,
            "MIN_display": "23:19"
          },
          "season_high": {
            "PTS": {
              "value": "8.0",
              "date": "2025-10-04",
              "opponent": "群馬クレインサンダーズ",
              "display": "8.0"
            },
            "REB": {
              "value": "4.0",
              "date": "2025-10-04",
              "opponent": "群馬クレインサンダーズ",
              "display": "4.0"
            },
            "AST": {
              "value": "1.0",
              "date": "2025-10-04",
              "opponent": "群馬クレインサンダーズ",
              "display": "1.0"
            },
            "3PM": {
              "value": "2.0",
              "date": "2025-10-04",
              "opponent": "群馬クレインサンダーズ",
              "display": "2.0"
            },
            "STL": {
              "value": "0.0",
              "date": "2025-10-04",
              "opponent": "群馬クレインサンダーズ",
              "display": "0.0"
            },
            "BLK": {
              "value": "0.0",
              "date": "2025-10-04",
              "opponent": "群馬クレインサンダーズ",
              "display": "0.0"
            },
            "MIN": {
              "value": "23.3167",
              "date": "2025-10-04",
              "opponent": "群馬クレインサンダーズ",
              "display": "23:19"
            }
          }
        },
        {
          "team_jba_id": "",
          "jersey_number": "13",
          "player_name": "侑太郎 須田",
          "stats": {
            "PTS": 7.0,
            "REB": 2.0,
            "AST": 0.0,
            "3PM": 1.0,
            "STL": 0.0,
            "BLK": 0.0,
            "MIN": 22.4333,
            "MIN_display": "22:26"
          },
          "season_high": {
            "PTS": {
              "value": "7.0",
              "date": "2025-10-04",
              "opponent": "群馬クレインサンダーズ",
              "display": "7.0"
            },
            "REB": {
              "value": "2.0",
              "date": "2025-10-04",
              "opponent": "群馬クレインサンダーズ",
              "display": "2.0"
            },
            "AST": {
              "value": "0.0",
              "date": "2025-10-04",
              "opponent": "群馬クレインサンダーズ",
              "display": "0.0"
            },
            "3PM": {
              "value": "1.0",
              "date": "2025-10-04",
              "opponent": "群馬クレインサンダーズ",
              "display": "1.0"
            },
            "STL": {
              "value": "0.0",
              "date": "2025-10-04",
              "opponent": "群馬クレインサンダーズ",
              "display": "0.0"
            },
            "BLK": {
              "value": "0.0",
              "date": "2025-10-04",
              "opponent": "群馬クレインサンダーズ",
              "display": "0.0"
            },
            "MIN": {
              "value": "22.4333",
              "date": "2025-10-04",
              "opponent": "群馬クレインサンダーズ",
              "display": "22:26"
            }
          }
        },
        {
          "team_jba_id": "",
          "jersey_number": "16",
          "player_name": "公陽 西田",
          "stats": {
            "PTS": 0.0,
            "REB": 0.0,
            "AST": 0.0,
            "3PM": 0.0,
            "STL": 0.0,
            "BLK": 0.0,
            "MIN": 4.5667,
            "MIN_display": "4:34"
          },
          "season_high": {
            "PTS": {
              "value": "0.0",
              "date": "2025-10-04",
              "opponent": "群馬クレインサンダーズ",
              "display": "0.0"
            },
            "REB": {
              "value": "0.0",
              "date": "2025-10-04",
              "opponent": "群馬クレインサンダーズ",
              "display": "0.0"
            },
            "AST": {
              "value": "0.0",
              "date": "2025-10-04",
              "opponent": "群馬クレインサンダーズ",
              "display": "0.0"
            },
            "3PM": {
              "value": "0.0",
              "date": "2025-10-04",
              "opponent": "群馬クレインサンダーズ",
              "display": "0.0"
            },
            "STL": {
              "value": "0.0",
              "date": "2025-10-04",
              "opponent": "群馬クレインサンダーズ",
              "display": "0.0"
            },
            "BLK": {
              "value": "0.0",
              "date": "2025-10-04",
              "opponent": "群馬クレインサンダーズ",
              "display": "0.0"
            },
            "MIN": {
              "value": "4.5667",
              "date": "2025-10-04",
              "opponent": "群馬クレインサンダーズ",
              "display": "4:34"
            }
          }
        },
        {
          "team_jba_id": "",
          "jersey_number": "18",
          "player_name": "亮伍 角野",
          "stats": {
            "PTS": 0.0,
            "REB": 1.0,
            "AST": 0.0,
            "3PM": 0.0,
            "STL": 0.0,
            "BLK": 0.0,
            "MIN": 14.7833,
            "MIN_display": "14:47"
          },
          "season_high": {
            "PTS": {
              "value": "0.0",
              "date": "2025-10-04",
              "opponent": "群馬クレインサンダーズ",
              "display": "0.0"
            },
            "REB": {
              "value": "1.0",
              "date": "2025-10-04",
              "opponent": "群馬クレインサンダーズ",
              "display": "1.0"
            },
            "AST": {
              "value": "0.0",
              "date": "2025-10-04",
              "opponent": "群馬クレインサンダーズ",
              "display": "0.0"
            },
            "3PM": {
              "value": "0.0",
              "date": "2025-10-04",
              "opponent": "群馬クレインサンダーズ",
              "display": "0.0"
            },
            "STL": {
              "value": "0.0",
              "date": "2025-10-04",
              "opponent": "群馬クレインサンダーズ",
              "display": "0.0"
            },
            "BLK": {
              "value": "0.0",
              "date": "2025-10-04",
              "opponent": "群馬クレインサンダーズ",
              "display": "0.0"
            },
            "MIN": {
              "value": "14.7833",
              "date": "2025-10-04",
              "opponent": "群馬クレインサンダーズ",
              "display": "14:47"
            }
          }
        },
        {
          "team_jba_id": "",
          "jersey_number": "19",
          "player_name": "優大 西田",
          "stats": {
            "PTS": 8.0,
            "REB": 3.0,
            "AST": 3.0,
            "3PM": 0.0,
            "STL": 0.0,
            "BLK": 0.0,
            "MIN": 25.1333,
            "MIN_display": "25:08"
          },
          "season_high": {
            "PTS": {
              "value": "8.0",
              "date": "2025-10-04",
              "opponent": "群馬クレインサンダーズ",
              "display": "8.0"
            },
            "REB": {
              "value": "3.0",
              "date": "2025-10-04",
              "opponent": "群馬クレインサンダーズ",
              "display": "3.0"
            },
            "AST": {
              "value": "3.0",
              "date": "2025-10-04",
              "opponent": "群馬クレインサンダーズ",
              "display": "3.0"
            },
            "3PM": {
              "value": "0.0",
              "date": "2025-10-04",
              "opponent": "群馬クレインサンダーズ",
              "display": "0.0"
            },
            "STL": {
              "value": "0.0",
              "date": "2025-10-04",
              "opponent": "群馬クレインサンダーズ",
              "display": "0.0"
            },
            "BLK": {
              "value": "0.0",
              "date": "2025-10-04",
              "opponent": "群馬クレインサンダーズ",
              "display": "0.0"
            },
            "MIN": {
              "value": "25.1333",
              "date": "2025-10-04",
              "opponent": "群馬クレインサンダーズ",
              "display": "25:08"
            }
          }
        },
        {
          "team_jba_id": "",
          "jersey_number": "27",
          "player_name": "講祐 石井",
          "stats": {
            "PTS": 0.0,
            "REB": 0.0,
            "AST": 0.0,
            "3PM": 0.0,
            "STL": 0.0,
            "BLK": 0.0,
            "MIN": 3.2167,
            "MIN_display": "3:13"
          },
          "season_high": {
            "PTS": {
              "value": "0.0",
              "date": "2025-10-04",
              "opponent": "群馬クレインサンダーズ",
              "display": "0.0"
            },
            "REB": {
              "value": "0.0",
              "date": "2025-10-04",
              "opponent": "群馬クレインサンダーズ",
              "display": "0.0"
            },
            "AST": {
              "value": "0.0",
              "date": "2025-10-04",
              "opponent": "群馬クレインサンダーズ",
              "display": "0.0"
            },
            "3PM": {
              "value": "0.0",
              "date": "2025-10-04",
              "opponent": "群馬クレインサンダーズ",
              "display": "0.0"
            },
            "STL": {
              "value": "0.0",
              "date": "2025-10-04",
              "opponent": "群馬クレインサンダーズ",
              "display": "0.0"
            },
            "BLK": {
              "value": "0.0",
              "date": "2025-10-04",
              "opponent": "群馬クレインサンダーズ",
              "display": "0.0"
            },
            "MIN": {
              "value": "3.2167",
              "date": "2025-10-04",
              "opponent": "群馬クレインサンダーズ",
              "display": "3:13"
            }
          }
        },
        {
          "team_jba_id": "",
          "jersey_number": "30",
          "player_name": "アーロン ホワイト",
          "stats": {
            "PTS": 11.0,
            "REB": 5.0,
            "AST": 1.0,
            "3PM": 1.0,
            "STL": 0.0,
            "BLK": 1.0,
            "MIN": 23.8333,
            "MIN_display": "23:50"
          },
          "season_high": {
            "PTS": {
              "value": "11.0",
              "date": "2025-10-04",
              "opponent": "群馬クレインサンダーズ",
              "display": "11.0"
            },
            "REB": {
              "value": "5.0",
              "date": "2025-10-04",
              "opponent": "群馬クレインサンダーズ",
              "display": "5.0"
            },
            "AST": {
              "value": "1.0",
              "date": "2025-10-04",
              "opponent": "群馬クレインサンダーズ",
              "display": "1.0"
            },
            "3PM": {
              "value": "1.0",
              "date": "2025-10-04",
              "opponent": "群馬クレインサンダーズ",
              "display": "1.0"
            },
            "STL": {
              "value": "0.0",
              "date": "2025-10-04",
              "opponent": "群馬クレインサンダーズ",
              "display": "0.0"
            },
            "BLK": {
              "value": "1.0",
              "date": "2025-10-04",
              "opponent": "群馬クレインサンダーズ",
              "display": "1.0"
            },
            "MIN": {
              "value": "23.8333",
              "date": "2025-10-04",
              "opponent": "群馬クレインサンダーズ",
              "display": "23:50"
            }
          }
        },
        {
          "team_jba_id": "",
          "jersey_number": "54",
          "player_name": "ダバンテ ガードナー",
          "stats": {
            "PTS": 16.0,
            "REB": 8.0,
            "AST": 3.0,
            "3PM": 1.0,
            "STL": 0.0,
            "BLK": 0.0,
            "MIN": 27.05,
            "MIN_display": "27:03"
          },
          "season_high": {
            "PTS": {
              "value": "16.0",
              "date": "2025-10-04",
              "opponent": "群馬クレインサンダーズ",
              "display": "16.0"
            },
            "REB": {
              "value": "8.0",
              "date": "2025-10-04",
              "opponent": "群馬クレインサンダーズ",
              "display": "8.0"
            },
            "AST": {
              "value": "3.0",
              "date": "2025-10-04",
              "opponent": "群馬クレインサンダーズ",
              "display": "3.0"
            },
            "3PM": {
              "value": "1.0",
              "date": "2025-10-04",
              "opponent": "群馬クレインサンダーズ",
              "display": "1.0"
            },
            "STL": {
              "value": "0.0",
              "date": "2025-10-04",
              "opponent": "群馬クレインサンダーズ",
              "display": "0.0"
            },
            "BLK": {
              "value": "0.0",
              "date": "2025-10-04",
              "opponent": "群馬クレインサンダーズ",
              "display": "0.0"
            },
            "MIN": {
              "value": "27.05",
              "date": "2025-10-04",
              "opponent": "群馬クレインサンダーズ",
              "display": "27:03"
            }
          }
        }
      ]
    },
    "群馬クレインサンダーズ": {
      "players": [
        {
          "team_jba_id": "",
          "jersey_number": "0",
          "player_name": "祐眞 藤井",
          "stats": {
            "PTS": 8.0,
            "REB": 0.0,
            "AST": 4.0,
            "3PM": 2.0,
            "STL": 2.0,
            "BLK": 0.0,
            "MIN": 22.6667,
            "MIN_display": "22:40"
          },
          "season_high": {
            "PTS": {
              "value": "8.0",
              "date": "2025-10-04",
              "opponent": "シーホース三河",
              "display": "8.0"
            },
            "REB": {
              "value": "0.0",
              "date": "2025-10-04",
              "opponent": "シーホース三河",
              "display": "0.0"
            },
            "AST": {
              "value": "4.0",
              "date": "2025-10-04",
              "opponent": "シーホース三河",
              "display": "4.0"
            },
            "3PM": {
              "value": "2.0",
              "date": "2025-10-04",
              "opponent": "シーホース三河",
              "display": "2.0"
            },
            "STL": {
              "value": "2.0",
              "date": "2025-10-04",
              "opponent": "シーホース三河",
              "display": "2.0"
            },
            "BLK": {
              "value": "0.0",
              "date": "2025-10-04",
              "opponent": "シーホース三河",
              "display": "0.0"
            },
            "MIN": {
              "value": "22.6667",
              "date": "2025-10-04",
              "opponent": "シーホース三河",
              "display": "22:40"
            }
          }
        },
        {
          "team_jba_id": "",
          "jersey_number": "1",
          "player_name": "コー フリッピン",
          "stats": {
            "PTS": 4.0,
            "REB": 1.0,
            "AST": 2.0,
            "3PM": 0.0,
            "STL": 1.0,
            "BLK": 0.0,
            "MIN": 10.2833,
            "MIN_display": "10:17"
          },
          "season_high": {
            "PTS": {
              "value": "4.0",
              "date": "2025-10-04",
              "opponent": "シーホース三河",
              "display": "4.0"
            },
            "REB": {
              "value": "1.0",
              "date": "2025-10-04",
              "opponent": "シーホース三河",
              "display": "1.0"
            },
            "AST": {
              "value": "2.0",
              "date": "2025-10-04",
              "opponent": "シーホース三河",
              "display": "2.0"
            },
            "3PM": {
              "value": "0.0",
              "date": "2025-10-04",
              "opponent": "シーホース三河",
              "display": "0.0"
            },
            "STL": {
              "value": "1.0",
              "date": "2025-10-04",
              "opponent": "シーホース三河",
              "display": "1.0"
            },
            "BLK": {
              "value": "0.0",
              "date": "2025-10-04",
              "opponent": "シーホース三河",
              "display": "0.0"
            },
            "MIN": {
              "value": "10.2833",
              "date": "2025-10-04",
              "opponent": "シーホース三河",
              "display": "10:17"
            }
          }
        },
        {
          "team_jba_id": "",
          "jersey_number": "4",
          "player_name": "トレイ ジョーンズ",
          "stats": {
            "PTS": 16.0,
            "REB": 7.0,
            "AST": 2.0,
            "3PM": 4.0,
            "STL": 1.0,
            "BLK": 1.0,
            "MIN": 27.3667,
            "MIN_display": "27:22"
          },
          "season_high": {
            "PTS": {
              "value": "16.0",
              "date": "2025-10-04",
              "opponent": "シーホース三河",
              "display": "16.0"
            },
            "REB": {
              "value": "7.0",
              "date": "2025-10-04",
              "opponent": "シーホース三河",
              "display": "7.0"
            },
            "AST": {
              "value": "2.0",
              "date": "2025-10-04",
              "opponent": "シーホース三河",
              "display": "2.0"
            },
            "3PM": {
              "value": "4.0",
              "date": "2025-10-04",
              "opponent": "シーホース三河",
              "display": "4.0"
            },
            "STL": {
              "value": "1.0",
              "date": "2025-10-04",
              "opponent": "シーホース三河",
              "display": "1.0"
            },
            "BLK": {
              "value": "1.0",
              "date": "2025-10-04",
              "opponent": "シーホース三河",
              "display": "1.0"
            },
            "MIN": {
              "value": "27.3667",
              "date": "2025-10-04",
              "opponent": "シーホース三河",
              "display": "27:22"
            }
          }
        },
        {
          "team_jba_id": "",
          "jersey_number": "6",
          "player_name": "拓人 中村",
          "stats": {
            "PTS": 6.0,
            "REB": 2.0,
            "AST": 2.0,
            "3PM": 1.0,
            "STL": 1.0,
            "BLK": 0.0,
            "MIN": 23.4,
            "MIN_display": "23:24"
          },
          "season_high": {
            "PTS": {
              "value": "6.0",
              "date": "2025-10-04",
              "opponent": "シーホース三河",
              "display": "6.0"
            },
            "REB": {
              "value": "2.0",
              "date": "2025-10-04",
              "opponent": "シーホース三河",
              "display": "2.0"
            },
            "AST": {
              "value": "2.0",
              "date": "2025-10-04",
              "opponent": "シーホース三河",
              "display": "2.0"
            },
            "3PM": {
              "value": "1.0",
              "date": "2025-10-04",
              "opponent": "シーホース三河",
              "display": "1.0"
            },
            "STL": {
              "value": "1.0",
              "date": "2025-10-04",
              "opponent": "シーホース三河",
              "display": "1.0"
            },
            "BLK": {
              "value": "0.0",
              "date": "2025-10-04",
              "opponent": "シーホース三河",
              "display": "0.0"
            },
            "MIN": {
              "value": "23.4",
              "date": "2025-10-04",
              "opponent": "シーホース三河",
              "display": "23:24"
            }
          }
        },
        {
          "team_jba_id": "",
          "jersey_number": "8",
          "player_name": "ケリー ブラックシアー・ジュニア",
          "stats": {
            "PTS": 17.0,
            "REB": 4.0,
            "AST": 3.0,
            "3PM": 0.0,
            "STL": 0.0,
            "BLK": 1.0,
            "MIN": 27.5167,
            "MIN_display": "27:31"
          },
          "season_high": {
            "PTS": {
              "value": "17.0",
              "date": "2025-10-04",
              "opponent": "シーホース三河",
              "display": "17.0"
            },
            "REB": {
              "value": "4.0",
              "date": "2025-10-04",
              "opponent": "シーホース三河",
              "display": "4.0"
            },
            "AST": {
              "value": "3.0",
              "date": "2025-10-04",
              "opponent": "シーホース三河",
              "display": "3.0"
            },
            "3PM": {
              "value": "0.0",
              "date": "2025-10-04",
              "opponent": "シーホース三河",
              "display": "0.0"
            },
            "STL": {
              "value": "0.0",
              "date": "2025-10-04",
              "opponent": "シーホース三河",
              "display": "0.0"
            },
            "BLK": {
              "value": "1.0",
              "date": "2025-10-04",
              "opponent": "シーホース三河",
              "display": "1.0"
            },
            "MIN": {
              "value": "27.5167",
              "date": "2025-10-04",
              "opponent": "シーホース三河",
              "display": "27:31"
            }
          }
        },
        {
          "team_jba_id": "",
          "jersey_number": "9",
          "player_name": "直人 辻",
          "stats": {
            "PTS": 2.0,
            "REB": 1.0,
            "AST": 1.0,
            "3PM": 0.0,
            "STL": 0.0,
            "BLK": 0.0,
            "MIN": 16.8667,
            "MIN_display": "16:52"
          },
          "season_high": {
            "PTS": {
              "value": "2.0",
              "date": "2025-10-04",
              "opponent": "シーホース三河",
              "display": "2.0"
            },
            "REB": {
              "value": "1.0",
              "date": "2025-10-04",
              "opponent": "シーホース三河",
              "display": "1.0"
            },
            "AST": {
              "value": "1.0",
              "date": "2025-10-04",
              "opponent": "シーホース三河",
              "display": "1.0"
            },
            "3PM": {
              "value": "0.0",
              "date": "2025-10-04",
              "opponent": "シーホース三河",
              "display": "0.0"
            },
            "STL": {
              "value": "0.0",
              "date": "2025-10-04",
              "opponent": "シーホース三河",
              "display": "0.0"
            },
            "BLK": {
              "value": "0.0",
              "date": "2025-10-04",
              "opponent": "シーホース三河",
              "display": "0.0"
            },
            "MIN": {
              "value": "16.8667",
              "date": "2025-10-04",
              "opponent": "シーホース三河",
              "display": "16:52"
            }
          }
        },
        {
          "team_jba_id": "",
          "jersey_number": "15",
          "player_name": "エージェー エドゥ",
          "stats": {
            "PTS": 8.0,
            "REB": 5.0,
            "AST": 2.0,
            "3PM": 0.0,
            "STL": 0.0,
            "BLK": 3.0,
            "MIN": 27.7667,
            "MIN_display": "27:46"
          },
          "season_high": {
            "PTS": {
              "value": "8.0",
              "date": "2025-10-04",
              "opponent": "シーホース三河",
              "display": "8.0"
            },
            "REB": {
              "value": "5.0",
              "date": "2025-10-04",
              "opponent": "シーホース三河",
              "display": "5.0"
            },
            "AST": {
              "value": "2.0",
              "date": "2025-10-04",
              "opponent": "シーホース三河",
              "display": "2.0"
            },
            "3PM": {
              "value": "0.0",
              "date": "2025-10-04",
              "opponent": "シーホース三河",
              "display": "0.0"
            },
            "STL": {
              "value": "0.0",
              "date": "2025-10-04",
              "opponent": "シーホース三河",
              "display": "0.0"
            },
            "BLK": {
              "value": "3.0",
              "date": "2025-10-04",
              "opponent": "シーホース三河",
              "display": "3.0"
            },
            "MIN": {
              "value": "27.7667",
              "date": "2025-10-04",
              "opponent": "シーホース三河",
              "display": "27:46"
            }
          }
        },
        {
          "team_jba_id": "",
          "jersey_number": "16",
          "player_name": "ケニー 淺野",
          "stats": {
            "PTS": 0.0,
            "REB": 0.0,
            "AST": 0.0,
            "3PM": 0.0,
            "STL": 0.0,
            "BLK": 0.0,
            "MIN": 0.7333,
            "MIN_display": "0:44"
          },
          "season_high": {
            "PTS": {
              "value": "0.0",
              "date": "2025-10-04",
              "opponent": "シーホース三河",
              "display": "0.0"
            },
            "REB": {
              "value": "0.0",
              "date": "2025-10-04",
              "opponent": "シーホース三河",
              "display": "0.0"
            },
            "AST": {
              "value": "0.0",
              "date": "2025-10-04",
              "opponent": "シーホース三河",
              "display": "0.0"
            },
            "3PM": {
              "value": "0.0",
              "date": "2025-10-04",
              "opponent": "シーホース三河",
              "display": "0.0"
            },
            "STL": {
              "value": "0.0",
              "date": "2025-10-04",
              "opponent": "シーホース三河",
              "display": "0.0"
            },
            "BLK": {
              "value": "0.0",
              "date": "2025-10-04",
              "opponent": "シーホース三河",
              "display": "0.0"
            },
            "MIN": {
              "value": "0.7333",
              "date": "2025-10-04",
              "opponent": "シーホース三河",
              "display": "0:44"
            }
          }
        },
        {
          "team_jba_id": "",
          "jersey_number": "29",
          "player_name": "一輝 細川",
          "stats": {
            "PTS": 8.0,
            "REB": 2.0,
            "AST": 0.0,
            "3PM": 2.0,
            "STL": 0.0,
            "BLK": 0.0,
            "MIN": 19.7,
            "MIN_display": "19:42"
          },
          "season_high": {
            "PTS": {
              "value": "8.0",
              "date": "2025-10-04",
              "opponent": "シーホース三河",
              "display": "8.0"
            },
            "REB": {
              "value": "2.0",
              "date": "2025-10-04",
              "opponent": "シーホース三河",
              "display": "2.0"
            },
            "AST": {
              "value": "0.0",
              "date": "2025-10-04",
              "opponent": "シーホース三河",
              "display": "0.0"
            },
            "3PM": {
              "value": "2.0",
              "date": "2025-10-04",
              "opponent": "シーホース三河",
              "display": "2.0"
            },
            "STL": {
              "value": "0.0",
              "date": "2025-10-04",
              "opponent": "シーホース三河",
              "display": "0.0"
            },
            "BLK": {
              "value": "0.0",
              "date": "2025-10-04",
              "opponent": "シーホース三河",
              "display": "0.0"
            },
            "MIN": {
              "value": "19.7",
              "date": "2025-10-04",
              "opponent": "シーホース三河",
              "display": "19:42"
            }
          }
        },
        {
          "team_jba_id": "",
          "jersey_number": "32",
          "player_name": "ヨハネス ティーマン",
          "stats": {
            "PTS": 6.0,
            "REB": 12.0,
            "AST": 0.0,
            "3PM": 0.0,
            "STL": 0.0,
            "BLK": 1.0,
            "MIN": 22.5667,
            "MIN_display": "22:34"
          },
          "season_high": {
            "PTS": {
              "value": "6.0",
              "date": "2025-10-04",
              "opponent": "シーホース三河",
              "display": "6.0"
            },
            "REB": {
              "value": "12.0",
              "date": "2025-10-04",
              "opponent": "シーホース三河",
              "display": "12.0"
            },
            "AST": {
              "value": "0.0",
              "date": "2025-10-04",
              "opponent": "シーホース三河",
              "display": "0.0"
            },
            "3PM": {
              "value": "0.0",
              "date": "2025-10-04",
              "opponent": "シーホース三河",
              "display": "0.0"
            },
            "STL": {
              "value": "0.0",
              "date": "2025-10-04",
              "opponent": "シーホース三河",
              "display": "0.0"
            },
            "BLK": {
              "value": "1.0",
              "date": "2025-10-04",
              "opponent": "シーホース三河",
              "display": "1.0"
            },
            "MIN": {
              "value": "22.5667",
              "date": "2025-10-04",
              "opponent": "シーホース三河",
              "display": "22:34"
            }
          }
        },
        {
          "team_jba_id": "",
          "jersey_number": "55",
          "player_name": "大智 谷口",
          "stats": {
            "PTS": 0.0,
            "REB": 1.0,
            "AST": 0.0,
            "3PM": 0.0,
            "STL": 0.0,
            "BLK": 0.0,
            "MIN": 1.1333,
            "MIN_display": "1:08"
          },
          "season_high": {
            "PTS": {
              "value": "0.0",
              "date": "2025-10-04",
              "opponent": "シーホース三河",
              "display": "0.0"
            },
            "REB": {
              "value": "1.0",
              "date": "2025-10-04",
              "opponent": "シーホース三河",
              "display": "1.0"
            },
            "AST": {
              "value": "0.0",
              "date": "2025-10-04",
              "opponent": "シーホース三河",
              "display": "0.0"
            },
            "3PM": {
              "value": "0.0",
              "date": "2025-10-04",
              "opponent": "シーホース三河",
              "display": "0.0"
            },
            "STL": {
              "value": "0.0",
              "date": "2025-10-04",
              "opponent": "シーホース三河",
              "display": "0.0"
            },
            "BLK": {
              "value": "0.0",
              "date": "2025-10-04",
              "opponent": "シーホース三河",
              "display": "0.0"
            },
            "MIN": {
              "value": "1.1333",
              "date": "2025-10-04",
              "opponent": "シーホース三河",
              "display": "1:08"
            }
          }
        }
      ]
    }
  }
}